main.py
py_terminal_clock-0.2.0.dist-info/METADATA
py_terminal_clock-0.2.0.dist-info/WHEEL
py_terminal_clock-0.2.0.dist-info/RECORD
