Metadata-Version: 2.3
Name: py-terminal-clock
Version: 0.2.0
Summary: A simple clock display for the terminal
Author-email: ffalcon31415 <77492177+ffalcon31415@users.noreply.github.com>
Requires-Python: >=3.9
Requires-Dist: pyfiglet>=1.0.2
